price_updater/.libcst.codemod.yaml
price_updater/.pylintrc
price_updater/__init__.py
price_updater/__main__.py
price_updater/api.py
price_updater/coins.txt
price_updater/coins_list.py
price_updater/data_translations.json
price_updater/formatting_editor.py
price_updater/Gabarito-SemiBold.ttf
price_updater/images/asset_logo/eur.png
price_updater/images/asset_logo/gbp.png
price_updater/images/asset_logo/ishares.png
price_updater/images/asset_logo/none.png
price_updater/images/asset_logo/usd.png
price_updater/images/asset_logo/xag.png
price_updater/images/asset_logo/xau.png
price_updater/images/background_logo.jpg
price_updater/images/background_sode.jpg
price_updater/images/logo.ico
price_updater/lib/__init__.py
price_updater/lib/asset.py
price_updater/lib/auto_suggestion_text.py
price_updater/lib/button.py
price_updater/lib/config.py
price_updater/lib/currency.py
price_updater/lib/language.py
price_updater/lib/on_check_box_active.py
price_updater/lib/settings.py
price_updater/lib/text_input.py
price_updater/lib/update.py
price_updater/mypy.ini
price_updater/scripts/black.sh
price_updater/scripts/mypy.sh
price_updater/scripts/precommit.sh
price_updater/scripts/pylint.sh
price_updater/widgets/__init__.py
price_updater/widgets/add_menu.py
price_updater/widgets/change_xlsx_menu.py
price_updater/widgets/coin_button.py
price_updater/widgets/install_update.bat
price_updater/widgets/install_update.sh
price_updater/widgets/menu.py
price_updater/widgets/modify_coin.py
price_updater/widgets/scroll_app.py
price_updater/widgets/top_bar.py
price_updater/widgets/version_available.py
price_updater-3.2.1.dist-info/METADATA
price_updater-3.2.1.dist-info/WHEEL
price_updater-3.2.1.dist-info/RECORD
