Metadata-Version: 2.3
Name: price-updater
Version: 3.2.1
Summary: Software for updating asset valuations in an XLSX spreadsheet.
License: Freeware
Author: Tomasz Kasperek
Requires-Python: >=3.10.9,<4.0.0
Classifier: License :: Other/Proprietary License
Classifier: Programming Language :: Python :: 3
Classifier: Programming Language :: Python :: 3.11
Classifier: Programming Language :: Python :: 3.12
Classifier: Programming Language :: Python :: 3.13
Requires-Dist: beautifulsoup4 (==4.12.2)
Requires-Dist: bs4 (==0.0.1)
Requires-Dist: kivy (>=2.2.1,<3.0.0)
Requires-Dist: kivymd (>=1.1.1,<2.0.0)
Requires-Dist: openpyxl (==3.1.2)
Requires-Dist: requests (==2.31.0)
Requires-Dist: xlib (==0.21)
